factorial_tnt/__init__.py
factorial_tnt/app.py
factorial_tnt/factorial.py
factorial_tnt-0.1.0.dist-info/METADATA
factorial_tnt-0.1.0.dist-info/WHEEL
factorial_tnt-0.1.0.dist-info/RECORD
