Metadata-Version: 2.1
Name: factorial-tnt
Version: 0.1.0
Summary: 
Author: TueNguyenTai
Author-email: nguyentaitue.2901@gmail.com
Requires-Python: >=3.10,<4.0
Classifier: Programming Language :: Python :: 3
Classifier: Programming Language :: Python :: 3.10
Classifier: Programming Language :: Python :: 3.11
Classifier: Programming Language :: Python :: 3.12
Requires-Dist: streamlit (>=1.39.0,<2.0.0)
